easyansi/__init__.py
easyansi/common/__init__.py
easyansi/common/field_validations.py
easyansi/common/regex_patterns.py
easyansi/core/__init__.py
easyansi/core/attributes.py
easyansi/core/color_builder.py
easyansi/core/colors.py
easyansi/core/core.py
easyansi/core/cursor.py
easyansi/core/screen.py
easyansi/core/utils.py
easyansi/drawing/__init__.py
easyansi/drawing/line_chars.py
easyansi/drawing/lines.py
easyansi/drawing/shapes.py
easy_ansi-2.1.1.dist-info/LICENSE
easy_ansi-2.1.1.dist-info/METADATA
easy_ansi-2.1.1.dist-info/WHEEL
easy_ansi-2.1.1.dist-info/top_level.txt
easy_ansi-2.1.1.dist-info/RECORD
